{
  "package": "APF_v35.2_G1_G6_NECESSITY_DERIVATION",
  "status": "G1_G6_NECESSITY_DERIVATION_PASS",
  "checks": "14/14 PASS",
  "version": "v35.2",
  "date": "2026-05-10",
  "session": "LATEST-19",
  "established": {
    "necessity": "G1-G6 are necessary conditions on any admissible trace-to-scheme transport, derivable from A1 + MD + BW + trace/scheme category structure",
    "audit_first_refusals_now_theorem_required": [
      "v18.0 W-route numeric projection (fails G5 + G6)",
      "v27 charged-lepton three-mode reconstruction (fails G5 + G6)",
      "v32 light-quark uniform scaling (fails G2 + G5)"
    ],
    "route_status_specificity_now_derived": "each route's status follows from which subset of G1-G6 it closes"
  },
  "open": {
    "sufficiency": "no-G7-exists by structural exhaustion of trace-to-scheme operation surfaces (next theorem program)",
    "uniqueness_of_status_determination": "each gate-availability pattern leads to exactly one named status (conjectural; empirically nine-for-nine)"
  },
  "lemmas": {
    "G1": {
      "name": "Codomain Identification",
      "foundation": "A1 + FD1 enforcement-substrate triple distinctness across interfaces"
    },
    "G2": {
      "name": "Transport Map Existence and Non-Inversion",
      "foundation": "A1 cost-payment for inter-category jump"
    },
    "G3": {
      "name": "External-Input Disclosure (Constants Ledger)",
      "foundation": "A1 no-overclaim corollary"
    },
    "G4": {
      "name": "Uncertainty Propagation",
      "foundation": "A1 + BW: bounded non-degenerate cost spectrum"
    },
    "G5": {
      "name": "No-Smuggling",
      "foundation": "Contrapositive of A1 applied to derivation"
    },
    "G6": {
      "name": "Residual Channel Assignment",
      "foundation": "A1 + MD: every distinction must have a paying ledger"
    }
  },
  "siblings": {
    "v35": "TRACE_TO_SCHEME_EXPORT_THEOREM_v35 — the export theorem itself (42/42 PASS)",
    "v35.1": "STRUCTURAL_EXTENSION_v35_1 — structural-codomain G4/G6 extension (9/9 PASS)",
    "v24.1_schema": "apf/codomain_transport_schema.py — codomain_type field applied to live bank (8/8 PASS post-extension)"
  },
  "next_theorem_programs": [
    "Sufficiency proof (no-G7-exists) by structural exhaustion of trace-to-scheme operation surfaces",
    "Uniqueness of route-status determination from gate-pattern combinatorics",
    "Bank module registering the six lemma statements as tier-3 [P_structural] checks (separate consideration)"
  ]
}
